submitify/__init__.py
submitify/apps.py
submitify/forms.py
submitify/models.py
submitify/tests.py
submitify/urls.py
submitify/migrations/0001_initial.py
submitify/migrations/0002_call_invite_only.py
submitify/migrations/0003_auto_20161124_0055.py
submitify/migrations/0004_auto_20161124_1926.py
submitify/migrations/0005_auto_20161204_0003.py
submitify/migrations/__init__.py
submitify/templates/submitify/manuscript.tex
submitify/templates/submitify/permission_denied.html
submitify/templates/submitify/calls/create.html
submitify/templates/submitify/calls/list.html
submitify/templates/submitify/calls/view.html
submitify/templates/submitify/notifications/create.html
submitify/templates/submitify/notifications/view.html
submitify/templates/submitify/reviews/view.html
submitify/templates/submitify/submissions/view.html
submitify/templates/submitify/submissions/view_text.html
submitify/views/__init__.py
submitify/views/calls.py
submitify/views/notifications.py
submitify/views/reviews.py
submitify/views/submissions.py
submitify/views/test_calls.py
submitify/views/test_notifications.py
submitify/views/test_reviews.py
submitify/views/test_submissions.py
submitify/views/__pycache__/__init__.cpython-37.pyc
submitify/views/__pycache__/calls.cpython-37.pyc
submitify/views/__pycache__/notifications.cpython-37.pyc
submitify/views/__pycache__/reviews.cpython-37.pyc
submitify/views/__pycache__/submissions.cpython-37.pyc
submitify/views/__pycache__/test_calls.cpython-37.pyc
submitify/views/__pycache__/test_notifications.cpython-37.pyc
submitify/views/__pycache__/test_reviews.cpython-37.pyc
submitify/views/__pycache__/test_submissions.cpython-37.pyc
submitify_standalone/__init__.py
submitify_standalone/settings.py
submitify_standalone/urls.py
submitify_standalone/wsgi.py
usermgmt_standalone/__init__.py
usermgmt_standalone/apps.py
usermgmt_standalone/forms.py
usermgmt_standalone/tests.py
usermgmt_standalone/urls.py
usermgmt_standalone/views.py
usermgmt_standalone/migrations/__init__.py
django_submitify-0.0.12.dist-info/LICENSE
django_submitify-0.0.12.dist-info/METADATA
django_submitify-0.0.12.dist-info/WHEEL
django_submitify-0.0.12.dist-info/top_level.txt
django_submitify-0.0.12.dist-info/RECORD
